camoufox_connector/__init__.py
camoufox_connector/config.py
camoufox_connector/health.py
camoufox_connector/pool.py
camoufox_connector/server.py
camoufox_connector-1.0.2.dist-info/licenses/LICENSE
camoufox_connector-1.0.2.dist-info/METADATA
camoufox_connector-1.0.2.dist-info/WHEEL
camoufox_connector-1.0.2.dist-info/entry_points.txt
camoufox_connector-1.0.2.dist-info/top_level.txt
camoufox_connector-1.0.2.dist-info/RECORD
