Metadata-Version: 2.4
Name: camoufox-connector
Version: 1.0.2
Summary: WebSocket bridge for multi-language Playwright access to Camoufox anti-detect browser
Author-email: Scrappey <info@scrappey.com>
License: MIT
Project-URL: Homepage, https://github.com/pim97/camoufox-connector
Project-URL: Documentation, https://github.com/pim97/camoufox-connector#readme
Project-URL: Repository, https://github.com/pim97/camoufox-connector
Project-URL: Issues, https://github.com/pim97/camoufox-connector/issues
Keywords: camoufox,playwright,websocket,anti-detect,browser,automation,scraping
Classifier: Development Status :: 4 - Beta
Classifier: Intended Audience :: Developers
Classifier: License :: OSI Approved :: MIT License
Classifier: Operating System :: OS Independent
Classifier: Programming Language :: Python :: 3
Classifier: Programming Language :: Python :: 3.9
Classifier: Programming Language :: Python :: 3.10
Classifier: Programming Language :: Python :: 3.11
Classifier: Programming Language :: Python :: 3.12
Classifier: Topic :: Internet :: WWW/HTTP :: Browsers
Classifier: Topic :: Software Development :: Libraries :: Python Modules
Requires-Python: >=3.9
License-File: LICENSE
Requires-Dist: camoufox[geoip]>=0.4.0
Requires-Dist: playwright>=1.40.0
Requires-Dist: pydantic>=2.0.0
Requires-Dist: pydantic-settings>=2.0.0
Requires-Dist: starlette>=0.35.0
Requires-Dist: uvicorn>=0.25.0
Requires-Dist: httpx>=0.26.0
Provides-Extra: dev
Requires-Dist: pytest>=7.0.0; extra == "dev"
Requires-Dist: pytest-asyncio>=0.23.0; extra == "dev"
Requires-Dist: black>=23.0.0; extra == "dev"
Requires-Dist: ruff>=0.1.0; extra == "dev"
Dynamic: license-file
